{
  "AU1000": "Los nombres son obligatorios.",
  "AU1001": "Los apellidos son obligatorios.",
  "AU1002": "El correo es obligatorio.",
  "AU1003": "La contraseña es obligatoria.",
  "AU1004": "El identificador es obligatorio.",
  "AU1005": "El teléfono es obligatorio.",
  "AU1103": "No se proporciona ningún token.",
  "AU1104": "Token no válido.",
  "AU1105": "La sesión ha expirado.",
  "AU5000": "Error interno del servidor.",
  "AU2000": "El usuario no ha sido creado.",
  "AU2001": "El usuario no tiene permisos.",
  "AU2002": "La contraseña es incorrecta.",
  "AU2003": "Se ha producido un error al enviar el correo electrónico de recuperación.",
  "AU2004": "El código no es válido.",
  "AC1000": "El dispositivo es obligatorio.",
  "AC1001": "La tag es obligatoria.",
  "AC1100": "El número de dispositivo no existe.",
  "AC1101": "El número de la tag no existe.",
  "AC1102": "La tag no está asignada a un usuario.",
  "AC1103": "Acceso denegado.",
  "AC1104": "No se ha proporcionado la API KEY.",
  "AC1105": "API KEY no es válida.",
  "AC5000": "Error interno del servidor.",
  "JR1100": "El código no existe en el archivo de errores json.",
  "JR1101": "El archivo de errores json no existe.",
  "DM1100": "El código del dispositivo ya ha sido utilizado.",
  "DM1101": "El dispositivo no existe.",
  "TM1100": "El código y número de la tarjeta ya han sido utilizados.",
  "TM1101": "La tarjeta no existe."
}
